README.md
setup.py
pyvagrant/__init__.py
pyvagrant/vagrant.py
pyvagrant.egg-info/PKG-INFO
pyvagrant.egg-info/SOURCES.txt
pyvagrant.egg-info/dependency_links.txt
pyvagrant.egg-info/entry_points.txt
pyvagrant.egg-info/requires.txt
pyvagrant.egg-info/top_level.txt
pyvagrant/box/__init__.py
pyvagrant/box/box.py
pyvagrant/cloud/__init__.py
pyvagrant/cloud/cloud.py
pyvagrant/plugins/__init__.py
pyvagrant/plugins/plugin.py
pyvagrant/plugins/plugins.py
vagrant_menu/__init__.py
vagrant_menu/menu.py