Metadata-Version: 2.1
Name: pyvagrant
Version: 0.2
Summary: Python wrapper around Vagrant.
Home-page: https://github.com/bannsec/pyvagrant
Author: Michael Bann
Author-email: self@bannsecurity.com
License: MIT
Keywords: vagrant
Platform: UNKNOWN
Classifier: Development Status :: 3 - Alpha
Classifier: Intended Audience :: End Users/Desktop
Classifier: License :: OSI Approved :: MIT License
Classifier: Programming Language :: Python :: 3
Classifier: Environment :: Console
Provides-Extra: dev
